{
  "openapi": "3.1.0",
  "info": {
    "title": "Tags",
    "description": "Manage tags to categorize contacts and deals.",
    "version": "1.0.0",
    "contact": { "name": "Vendaze Support", "email": "suporte@vendaze.com" }
  },
  "servers": [{ "url": "https://api.vendaze.com", "description": "Production" }],
  "security": [{ "bearerAuth": [] }],
  "tags": [{ "name": "Tags" }],
  "paths": {
    "/v1/tags": {
      "get": {
        "operationId": "listTags",
        "summary": "List tags",
        "description": "Returns all tags in the workspace.",
        "tags": ["Tags"],
        "parameters": [
          { "$ref": "#/components/parameters/page" },
          { "$ref": "#/components/parameters/per_page" },
          { "$ref": "#/components/parameters/order_by" },
          { "$ref": "#/components/parameters/order" }
        ],
        "responses": {
          "200": {
            "description": "List of tags returned successfully.",
            "content": { "application/json": { "schema": { "$ref": "#/components/schemas/TagsListResponse" } } }
          },
          "401": { "$ref": "#/components/responses/Unauthorized" },
          "403": { "$ref": "#/components/responses/InsufficientScope" },
          "422": { "$ref": "#/components/responses/ValidationError" },
          "429": { "$ref": "#/components/responses/RateLimitExceeded" }
        }
      },
      "post": {
        "operationId": "createTag",
        "summary": "Create a tag",
        "description": "Creates a new tag in the workspace.",
        "tags": ["Tags"],
        "requestBody": {
          "required": true,
          "content": { "application/json": { "schema": { "$ref": "#/components/schemas/CreateTagRequest" } } }
        },
        "responses": {
          "201": {
            "description": "Tag created successfully.",
            "content": { "application/json": { "schema": { "$ref": "#/components/schemas/TagResponse" } } }
          },
          "401": { "$ref": "#/components/responses/Unauthorized" },
          "403": { "$ref": "#/components/responses/InsufficientScope" },
          "422": { "$ref": "#/components/responses/ValidationError" },
          "429": { "$ref": "#/components/responses/RateLimitExceeded" }
        }
      }
    },
    "/v1/tags/{id}": {
      "get": {
        "operationId": "getTag",
        "summary": "Get a tag",
        "description": "Returns a tag by ID.",
        "tags": ["Tags"],
        "parameters": [{ "$ref": "#/components/parameters/id" }],
        "responses": {
          "200": {
            "description": "Tag returned successfully.",
            "content": { "application/json": { "schema": { "$ref": "#/components/schemas/TagResponse" } } }
          },
          "401": { "$ref": "#/components/responses/Unauthorized" },
          "403": { "$ref": "#/components/responses/InsufficientScope" },
          "404": { "$ref": "#/components/responses/NotFound" }
        }
      },
      "patch": {
        "operationId": "updateTag",
        "summary": "Update a tag",
        "description": "Updates a tag. Only fields included in the body are modified.",
        "tags": ["Tags"],
        "parameters": [{ "$ref": "#/components/parameters/id" }],
        "requestBody": {
          "required": true,
          "content": { "application/json": { "schema": { "$ref": "#/components/schemas/UpdateTagRequest" } } }
        },
        "responses": {
          "200": {
            "description": "Tag updated successfully.",
            "content": { "application/json": { "schema": { "$ref": "#/components/schemas/TagResponse" } } }
          },
          "401": { "$ref": "#/components/responses/Unauthorized" },
          "403": { "$ref": "#/components/responses/InsufficientScope" },
          "404": { "$ref": "#/components/responses/NotFound" },
          "422": { "$ref": "#/components/responses/ValidationError" }
        }
      },
      "delete": {
        "operationId": "deleteTag",
        "summary": "Delete a tag",
        "description": "Soft-delete: the record is no longer accessible via the API.",
        "tags": ["Tags"],
        "parameters": [{ "$ref": "#/components/parameters/id" }],
        "responses": {
          "204": { "description": "Tag deleted successfully." },
          "401": { "$ref": "#/components/responses/Unauthorized" },
          "403": { "$ref": "#/components/responses/InsufficientScope" },
          "404": { "$ref": "#/components/responses/NotFound" }
        }
      }
    }
  },
  "components": {
    "securitySchemes": {
      "bearerAuth": { "type": "http", "scheme": "bearer", "description": "OAuth 2.1 access token." }
    },
    "parameters": {
      "id": {
        "name": "id",
        "in": "path",
        "required": true,
        "schema": { "type": "string", "format": "uuid" },
        "description": "UUID of the resource."
      },
      "page": { "name": "page", "in": "query", "schema": { "type": "integer", "default": 1, "minimum": 1 } },
      "per_page": {
        "name": "per_page",
        "in": "query",
        "schema": { "type": "integer", "default": 50, "minimum": 1, "maximum": 100 },
        "description": "Max 100."
      },
      "order_by": { "name": "order_by", "in": "query", "schema": { "type": "string", "default": "created_at" } },
      "order": { "name": "order", "in": "query", "schema": { "type": "string", "enum": ["asc", "desc"], "default": "desc" } },
      "created_after": { "name": "created_after", "in": "query", "schema": { "type": "string", "format": "date-time" } },
      "created_before": { "name": "created_before", "in": "query", "schema": { "type": "string", "format": "date-time" } },
      "updated_after": { "name": "updated_after", "in": "query", "schema": { "type": "string", "format": "date-time" } },
      "updated_before": { "name": "updated_before", "in": "query", "schema": { "type": "string", "format": "date-time" } }
    },
    "responses": {
      "Unauthorized": {
        "description": "Missing or invalid token.",
        "content": { "application/json": { "schema": { "$ref": "#/components/schemas/ErrorResponse" } } }
      },
      "InsufficientScope": {
        "description": "Token lacks the required scope.",
        "content": { "application/json": { "schema": { "$ref": "#/components/schemas/ErrorResponse" } } }
      },
      "NotFound": {
        "description": "Resource not found.",
        "content": { "application/json": { "schema": { "$ref": "#/components/schemas/ErrorResponse" } } }
      },
      "ValidationError": {
        "description": "Input validation failed.",
        "content": { "application/json": { "schema": { "$ref": "#/components/schemas/ValidationErrorResponse" } } }
      },
      "RateLimitExceeded": {
        "description": "Rate limit exceeded.",
        "content": { "application/json": { "schema": { "$ref": "#/components/schemas/ErrorResponse" } } }
      }
    },
    "schemas": {
      "ErrorResponse": {
        "type": "object",
        "properties": {
          "error": {
            "type": "object",
            "properties": {
              "code": { "type": "string", "example": "not_found" },
              "message": { "type": "string", "example": "Resource not found." },
              "request_id": { "type": "string", "format": "uuid" }
            }
          }
        }
      },
      "ValidationErrorResponse": {
        "type": "object",
        "properties": {
          "error": {
            "type": "object",
            "properties": {
              "code": { "type": "string", "example": "validation_error" },
              "message": { "type": "string", "example": "Validation failed." },
              "fields": { "type": "object", "additionalProperties": { "type": "string" } },
              "request_id": { "type": "string", "format": "uuid" }
            }
          }
        }
      },
      "PaginationMeta": {
        "type": "object",
        "properties": {
          "total": { "type": "integer", "example": 150 },
          "page": { "type": "integer", "example": 1 },
          "per_page": { "type": "integer", "example": 50 },
          "has_more": { "type": "boolean", "example": true }
        }
      },
      "ContactEmail": {
        "type": "object",
        "required": ["email"],
        "properties": {
          "email": { "type": "string", "format": "email", "example": "nome@empresa.com" },
          "reminder": {
            "type": "string",
            "enum": ["personal", "work", "other"],
            "description": "Type of email. Accepted values: personal, work, other.",
            "example": "work"
          }
        },
        "example": { "email": "nome@empresa.com", "reminder": "work" }
      },
      "ContactPhone": {
        "type": "object",
        "required": ["phone"],
        "properties": {
          "phone": { "type": "string", "example": "+5511999990001" },
          "reminder": {
            "type": "string",
            "enum": ["mobile", "work", "residential", "other"],
            "description": "Type of phone. Accepted values: mobile, work, residential, other.",
            "example": "mobile"
          }
        },
        "example": { "phone": "+5511999990001", "reminder": "mobile" }
      },
      "Tag": {
        "type": "object",
        "properties": {
          "id": { "type": "string", "format": "uuid" },
          "name": { "type": "string", "maxLength": 30, "example": "vip-client" },
          "color_text": { "type": "string", "nullable": true, "example": "#ffffff" },
          "color_background": { "type": "string", "nullable": true, "example": "#0085c0" },
          "created_at": { "type": "string", "format": "date-time" }
        }
      },
      "CreateTagRequest": {
        "type": "object",
        "required": ["name"],
        "properties": {
          "name": { "type": "string", "maxLength": 30, "example": "vip-client" },
          "color_text": { "type": "string", "example": "#ffffff" },
          "color_background": { "type": "string", "example": "#0085c0" }
        }
      },
      "UpdateTagRequest": {
        "type": "object",
        "properties": {
          "name": { "type": "string", "maxLength": 30 },
          "color_text": { "type": "string", "nullable": true },
          "color_background": { "type": "string", "nullable": true }
        }
      },
      "TagsListResponse": {
        "type": "object",
        "properties": {
          "data": { "type": "array", "items": { "$ref": "#/components/schemas/Tag" } },
          "meta": { "$ref": "#/components/schemas/PaginationMeta" }
        }
      },
      "TagResponse": {
        "type": "object",
        "properties": {
          "data": { "$ref": "#/components/schemas/Tag" }
        }
      }
    }
  }
}
